[
  {
    "name": "CA de l’Ouest Rhodanien",
    "code": "200040566"
  },
  {
    "name": "CC Beaujolais Pierres Dorées",
    "code": "200040574"
  },
  {
    "name": "CA Villefranche Beaujolais Saône",
    "code": "200040590"
  },
  {
    "name": "Métropole de Lyon",
    "code": "200046977"
  },
  {
    "name": "CC des Monts du Lyonnais",
    "code": "200066587"
  },
  {
    "name": "CC Saône-Beaujolais",
    "code": "200067817"
  },
  {
    "name": "CA Vienne Condrieu",
    "code": "200077014"
  },
  {
    "name": "CC de l’Est Lyonnais (CCEL)",
    "code": "246900575"
  },
  {
    "name": "CC du Pays de l’Arbresle (CCPA)",
    "code": "246900625"
  },
  {
    "name": "CC des Vallons du Lyonnais (CCVL)",
    "code": "246900724"
  },
  {
    "name": "CC du Pays Mornantais (COPAMO)",
    "code": "246900740"
  },
  {
    "name": "CC de la Vallée du Garon (CCVG)",
    "code": "246900757"
  },
  {
    "name": "CC du Pays de l’Ozon",
    "code": "246900765"
  }
]