[
  {
    "name": "CC Coeur de Tarentaise",
    "code": "200023299"
  },
  {
    "name": "CC Coeur de Chartreuse",
    "code": "200040111"
  },
  {
    "name": "CC Val Vanoise",
    "code": "200040798"
  },
  {
    "name": "CC Coeur de Savoie",
    "code": "200041010"
  },
  {
    "name": "CA Grand Lac",
    "code": "200068674"
  },
  {
    "name": "CA Arlysère",
    "code": "200068997"
  },
  {
    "name": "CA du Grand Chambéry",
    "code": "200069110"
  },
  {
    "name": "CC Haute Maurienne Vanoise",
    "code": "200070340"
  },
  {
    "name": "CC Coeur de Maurienne Arvan",
    "code": "200070464"
  },
  {
    "name": "CC des Vallées d’Aigueblanche",
    "code": "247300015"
  },
  {
    "name": "CC de Haute-Tarentaise",
    "code": "247300254"
  },
  {
    "name": "CC de Yenne",
    "code": "247300262"
  },
  {
    "name": "CC du Canton de La Chambre",
    "code": "247300361"
  },
  {
    "name": "CC Maurienne Galibier",
    "code": "247300452"
  },
  {
    "name": "CC Val Guiers",
    "code": "247300528"
  },
  {
    "name": "CC du Lac d’Aiguebelette (CCLA)",
    "code": "247300668"
  },
  {
    "name": "CC Porte de Maurienne",
    "code": "247300676"
  },
  {
    "name": "CC Les Versants d’Aime",
    "code": "247300817"
  }
]